cert_core/__init__.py
cert_core/cert_model/__init__.py
cert_core/cert_model/model.py
cert_core/cert_store/__init__.py
cert_core/cert_store/certificate_store.py
cert_core/cert_store/config.py
cert_core/cert_store/gridfs_key_value_store.py
cert_core/cert_store/helpers.py
cert_core_bloxberg2-1.0.0.dist-info/licenses/LICENSE
tests/__init__.py
tests/test_certificate_store.py
tests/test_init.py
tests/test_model.py
cert_core_bloxberg2-1.0.0.dist-info/METADATA
cert_core_bloxberg2-1.0.0.dist-info/WHEEL
cert_core_bloxberg2-1.0.0.dist-info/top_level.txt
cert_core_bloxberg2-1.0.0.dist-info/RECORD
