Metadata-Version: 2.4
Name: cert-core-bloxberg2
Version: 1.0.0
Summary: Blockcerts core models for python
Home-page: https://gitlab.mpcdf.mpg.de/cert-issuer/cert-core.git
Author: info@blockcerts.org
Author-email: info@blockcerts.org
License: MIT
License-File: LICENSE
Requires-Dist: requests>=2.18.4
Requires-Dist: cert-schema>=2.1.5
Requires-Dist: configargparse>=0.12.0
Requires-Dist: connexion>=1.1.14
Requires-Dist: enum34>=1.1.6; python_version < "3.4"
Requires-Dist: Flask-PyMongo>=0.5.1
Requires-Dist: jsonschema>=2.6.0
Requires-Dist: python-dateutil>=2.6.1
Requires-Dist: pytz>=2017.2
Requires-Dist: simplekv>=0.10.0
Requires-Dist: tox>=3.0.0
Requires-Dist: validators>=0.12.1
Dynamic: author
Dynamic: author-email
Dynamic: description
Dynamic: description-content-type
Dynamic: home-page
Dynamic: license
Dynamic: license-file
Dynamic: requires-dist
Dynamic: summary
